osmtogtfs/ODbL-1.0.txt
osmtogtfs/__init__.py
osmtogtfs/cli.py
osmtogtfs/gtfs/__init__.py
osmtogtfs/gtfs/gtfs_dummy.py
osmtogtfs/gtfs/gtfs_misc.py
osmtogtfs/gtfs/gtfs_writer.py
osmtogtfs/osm/__init__.py
osmtogtfs/osm/exporter.py
osmtogtfs/osm/models.py
osmtogtfs/osm/builders/__init__.py
osmtogtfs/osm/builders/agency_builder.py
osmtogtfs/osm/builders/route_builder.py
osmtogtfs/osm/builders/shape_builder.py
osmtogtfs/osm/builders/stop_builder.py
osmtogtfs/osm/handlers/__init__.py
osmtogtfs/osm/handlers/node_handler.py
osmtogtfs/osm/handlers/relation_handler.py
osmtogtfs/osm/handlers/way_handler.py
osmtogtfs/tests/__init__.py
osmtogtfs/tests/test_validation.py
osmtogtfs-0.4.3.dist-info/entry_points.txt
osmtogtfs-0.4.3.dist-info/LICENSE
osmtogtfs-0.4.3.dist-info/WHEEL
osmtogtfs-0.4.3.dist-info/METADATA
osmtogtfs-0.4.3.dist-info/RECORD
