Metadata-Version: 2.1
Name: osmtogtfs
Version: 0.4.3
Summary: osmtogtfs is a tool to extract public transport information from OpenStreetMap
Home-page: https://github.com/hiposfer/osmtogtfs
License: UNKNOWN
Keywords: osm gtfs
Author: Mehdi Sadeghi
Author-email: mehdi@mehdix.rog
Requires-Python: >=3.5
Classifier: Development Status :: 4 - Beta
Classifier: Intended Audience :: Developers
Classifier: License :: OSI Approved :: MIT License
Classifier: Programming Language :: Python :: 3
Requires-Dist: osmium
Requires-Dist: pytest; extra == "test"
Requires-Dist: bottle; extra == "web"
Provides-Extra: .none
Provides-Extra: test
Provides-Extra: web
